arclio_mcp_gsuite/__init__.py
arclio_mcp_gsuite/__main__.py
arclio_mcp_gsuite/app.py
arclio_mcp_gsuite/config.py
arclio_mcp_gsuite/auth/__init__.py
arclio_mcp_gsuite/auth/gauth.py
arclio_mcp_gsuite/prompts/__init__.py
arclio_mcp_gsuite/prompts/calendar.py
arclio_mcp_gsuite/prompts/drive.py
arclio_mcp_gsuite/prompts/gmail.py
arclio_mcp_gsuite/prompts/slides.py
arclio_mcp_gsuite/resources/__init__.py
arclio_mcp_gsuite/resources/calendar.py
arclio_mcp_gsuite/resources/drive.py
arclio_mcp_gsuite/resources/gmail.py
arclio_mcp_gsuite/resources/slides.py
arclio_mcp_gsuite/services/__init__.py
arclio_mcp_gsuite/services/base.py
arclio_mcp_gsuite/services/calendar.py
arclio_mcp_gsuite/services/drive.py
arclio_mcp_gsuite/services/gmail.py
arclio_mcp_gsuite/services/slides.py
arclio_mcp_gsuite/tools/__init__.py
arclio_mcp_gsuite/tools/calendar.py
arclio_mcp_gsuite/tools/drive.py
arclio_mcp_gsuite/tools/gmail.py
arclio_mcp_gsuite/tools/slides.py
arclio_mcp_gsuite/utils/__init__.py
arclio_mcp_gsuite/utils/markdown_slides.py
arclio_mcp_gsuite-0.1.3.dist-info/METADATA
arclio_mcp_gsuite-0.1.3.dist-info/WHEEL
arclio_mcp_gsuite-0.1.3.dist-info/entry_points.txt
arclio_mcp_gsuite-0.1.3.dist-info/RECORD
