Metadata-Version: 2.4
Name: arclio-mcp-gsuite
Version: 0.1.3
Summary: MCP server for Google Workspace integration
Author-email: Arclio Team <info@arclio.com>
License: MIT
Requires-Python: >=3.10
Requires-Dist: beautifulsoup4>=4.12.0
Requires-Dist: google-api-python-client>=2.86.0
Requires-Dist: google-auth-httplib2>=0.1.0
Requires-Dist: google-auth-oauthlib>=1.0.0
Requires-Dist: google-auth>=2.22.0
Requires-Dist: markdown>=3.5.0
Requires-Dist: markdowndeck>=0.1.0
Requires-Dist: mcp>=1.7.0
Requires-Dist: python-dotenv>=1.0.0
Requires-Dist: pytz>=2023.3
Provides-Extra: dev
